distilabel_cost_calculator/__init__.py
distilabel_cost_calculator/config/api_pricing.yaml
distilabel_cost_calculator/config/api_pricing_config.py
distilabel_cost_calculator/generation_step_cost.py
distilabel_cost_calculator-0.2.1.dist-info/METADATA
distilabel_cost_calculator-0.2.1.dist-info/WHEEL
distilabel_cost_calculator-0.2.1.dist-info/RECORD
