Metadata-Version: 2.1
Name: distilabel-cost-calculator
Version: 0.2.1
Summary: A custom Step for LLM API cost calculation for the distilabel library.
Author: Djellal Mohamed Aniss
Author-email: djellalmohamedaniss@outlook.com
Requires-Python: >=3.10.15,<4.0.0
Classifier: Programming Language :: Python :: 3
Classifier: Programming Language :: Python :: 3.11
Classifier: Programming Language :: Python :: 3.12
Requires-Dist: pyyaml (>=6.0.2,<7.0.0)
Requires-Dist: tiktoken (>=0.8.0,<0.9.0)
